{
  "node": {
    "408732526b0913eda4735601a76db162d32df5fe32": {
      "workers": {
        "app/sandbox/page": {
          "moduleId": 84733,
          "async": false,
          "exportedName": "createApiKey",
          "filename": "apps/example/app/actions.ts"
        }
      },
      "layer": {
        "app/sandbox/page": "action-browser"
      },
      "exportedName": "createApiKey",
      "filename": "apps/example/app/actions.ts"
    },
    "40e8f93476dd15da485b5ff2a12d60fd762c71ad85": {
      "workers": {
        "app/sandbox/page": {
          "moduleId": 84733,
          "async": false,
          "exportedName": "disableApiKey",
          "filename": "apps/example/app/actions.ts"
        }
      },
      "layer": {
        "app/sandbox/page": "action-browser"
      },
      "exportedName": "disableApiKey",
      "filename": "apps/example/app/actions.ts"
    },
    "409d127c0868472cec5e54d503758f119da551b4d4": {
      "workers": {
        "app/sandbox/page": {
          "moduleId": 84733,
          "async": false,
          "exportedName": "enableApiKey",
          "filename": "apps/example/app/actions.ts"
        }
      },
      "layer": {
        "app/sandbox/page": "action-browser"
      },
      "exportedName": "enableApiKey",
      "filename": "apps/example/app/actions.ts"
    },
    "60806188deb87fd6c48c5ae501633ab3be95ee8919": {
      "workers": {
        "app/sandbox/page": {
          "moduleId": 84733,
          "async": false,
          "exportedName": "getAuditLogs",
          "filename": "apps/example/app/actions.ts"
        }
      },
      "layer": {
        "app/sandbox/page": "action-browser"
      },
      "exportedName": "getAuditLogs",
      "filename": "apps/example/app/actions.ts"
    },
    "40434dc93db41af65e7dd89d0ae199b39810aa8010": {
      "workers": {
        "app/sandbox/page": {
          "moduleId": 84733,
          "async": false,
          "exportedName": "listApiKeys",
          "filename": "apps/example/app/actions.ts"
        }
      },
      "layer": {
        "app/sandbox/page": "action-browser"
      },
      "exportedName": "listApiKeys",
      "filename": "apps/example/app/actions.ts"
    },
    "4051a801f13e8e188c604b84e2fc63c1af815a0996": {
      "workers": {
        "app/sandbox/page": {
          "moduleId": 84733,
          "async": false,
          "exportedName": "revokeApiKey",
          "filename": "apps/example/app/actions.ts"
        }
      },
      "layer": {
        "app/sandbox/page": "action-browser"
      },
      "exportedName": "revokeApiKey",
      "filename": "apps/example/app/actions.ts"
    },
    "40a9d7c13b536f78b091282c2bb9aef4f0e1d1a1a7": {
      "workers": {
        "app/sandbox/page": {
          "moduleId": 84733,
          "async": false,
          "exportedName": "rotateApiKey",
          "filename": "apps/example/app/actions.ts"
        }
      },
      "layer": {
        "app/sandbox/page": "action-browser"
      },
      "exportedName": "rotateApiKey",
      "filename": "apps/example/app/actions.ts"
    },
    "40ec5adf8ddb3c36d5f760992d5bbd19e37a53ff6d": {
      "workers": {
        "app/sandbox/page": {
          "moduleId": 84733,
          "async": false,
          "exportedName": "verifyApiKey",
          "filename": "apps/example/app/actions.ts"
        }
      },
      "layer": {
        "app/sandbox/page": "action-browser"
      },
      "exportedName": "verifyApiKey",
      "filename": "apps/example/app/actions.ts"
    },
    "7097902fa6daaa473361709b73c7e03e6687657cfb": {
      "workers": {
        "app/sandbox/page": {
          "moduleId": 84733,
          "async": false,
          "exportedName": "verifyApiKeyWithScopes",
          "filename": "apps/example/app/actions.ts"
        }
      },
      "layer": {
        "app/sandbox/page": "action-browser"
      },
      "exportedName": "verifyApiKeyWithScopes",
      "filename": "apps/example/app/actions.ts"
    }
  },
  "edge": {}
}